CHANGES.txt
CONTRIBUTORS.txt
KNOWN_ISSUES.txt
README.txt
setup.py
betahaus/__init__.py
betahaus.memberprofile.egg-info/PKG-INFO
betahaus.memberprofile.egg-info/SOURCES.txt
betahaus.memberprofile.egg-info/dependency_links.txt
betahaus.memberprofile.egg-info/entry_points.txt
betahaus.memberprofile.egg-info/namespace_packages.txt
betahaus.memberprofile.egg-info/not-zip-safe
betahaus.memberprofile.egg-info/requires.txt
betahaus.memberprofile.egg-info/top_level.txt
betahaus/memberprofile/TODO.txt
betahaus/memberprofile/__init__.py
betahaus/memberprofile/adapters.py
betahaus/memberprofile/config.py
betahaus/memberprofile/configure.zcml
betahaus/memberprofile/handlers.py
betahaus/memberprofile/interfaces.py
betahaus/memberprofile/permissions.py
betahaus/memberprofile/rebuild-i18n.sh
betahaus/memberprofile/setuphandlers.py
betahaus/memberprofile/utilities.py
betahaus/memberprofile/validators.py
betahaus/memberprofile/browser/__init__.py
betahaus/memberprofile/browser/configure.zcml
betahaus/memberprofile/browser/controlpanel.py
betahaus/memberprofile/browser/interfaces.py
betahaus/memberprofile/browser/redirect.py
betahaus/memberprofile/content/__init__.py
betahaus/memberprofile/content/configure.zcml
betahaus/memberprofile/content/interfaces.py
betahaus/memberprofile/content/memberprofile.py
betahaus/memberprofile/content/mixin.py
betahaus/memberprofile/locales/betahaus.memberprofile.pot
betahaus/memberprofile/locales/manual.pot
betahaus/memberprofile/locales/sv/LC_MESSAGES/betahaus.memberprofile.po
betahaus/memberprofile/profiles/default/actions.xml
betahaus/memberprofile/profiles/default/browserlayer.xml
betahaus/memberprofile/profiles/default/controlpanel.xml
betahaus/memberprofile/profiles/default/factorytool.xml
betahaus/memberprofile/profiles/default/memberdata_properties.xml
betahaus/memberprofile/profiles/default/memberprofile_marker.txt
betahaus/memberprofile/profiles/default/metadata.xml
betahaus/memberprofile/profiles/default/rolemap.xml
betahaus/memberprofile/profiles/default/skins.xml
betahaus/memberprofile/profiles/default/tinymce.xml
betahaus/memberprofile/profiles/default/types.xml
betahaus/memberprofile/profiles/default/types/MemberProfile.xml
betahaus/memberprofile/skins/betahaus_memberprofile_skins/author.py
betahaus/memberprofile/skins/betahaus_memberprofile_skins/dashboard.py
betahaus/memberprofile/tests/__init__.py
