Metadata-Version: 1.0
Name: betahaus.memberprofile
Version: 0.2rc1
Summary: Flexible member profiles for Plone
Home-page: http://dev.betahaus.net
Author: Robin Harms Oredsson, Martin Lundwall et.al.
Author-email: robin@betahaus.net
License: GPL
Keywords: plone
Platform: UNKNOWN
Classifier: Development Status :: 4 - Beta
Classifier: Framework :: Plone
Classifier: Programming Language :: Python
Classifier: Topic :: Software Development :: Libraries :: Python Modules
